apikit/__init__.py
apikit/args.py
apikit/authz.py
apikit/cache.py
apikit/jsonify.py
apikit/pager.py
apikit-0.4.dist-info/METADATA
apikit-0.4.dist-info/RECORD
apikit-0.4.dist-info/WHEEL
apikit-0.4.dist-info/namespace_packages.txt
apikit-0.4.dist-info/top_level.txt
